_ROL.cpython-38-x86_64-linux-gnu.so
librol.so
librol.so.15
librol.so.15.1
libteuchoscomm.so
libteuchoscomm.so.15
libteuchoscomm.so.15.1
libteuchoscore.so
libteuchoscore.so.15
libteuchoscore.so.15.1
libteuchosnumerics.so
libteuchosnumerics.so.15
libteuchosnumerics.so.15.1
libteuchosparameterlist.so
libteuchosparameterlist.so.15
libteuchosparameterlist.so.15.1
libteuchosparser.so
libteuchosparser.so.15
libteuchosparser.so.15.1
libteuchosremainder.so
libteuchosremainder.so.15
libteuchosremainder.so.15.1
ROL/ROL.cpp
ROL/__init__.py
ROL/algorithm.cpp
ROL/algorithmstate.cpp
ROL/augmentedlagrangian.cpp
ROL/bounds.cpp
ROL/constraint.cpp
ROL/dolfin_vector.py
ROL/firedrake_vector.py
ROL/numpy_vector.py
ROL/objective.cpp
ROL/optimizationproblem.cpp
ROL/optimizationsolver.cpp
ROL/parameterlist.cpp
ROL/problem.cpp
ROL/py_shared_ptr.hpp
ROL/secant.cpp
ROL/solver.cpp
ROL/statustest.cpp
ROL/stdvector.cpp
ROL/step.cpp
ROL/vector.cpp
ROL/vector.hpp
pyroltrilinos.libs/libgcc_s-0cd532bd.so.1
pyroltrilinos.libs/libgfortran-2c33b284.so.5.0.0
pyroltrilinos.libs/libopenblasp-r0-73d5d8f8.3.28.so
pyroltrilinos.libs/libquadmath-bb76a5fc.so.0.0.0
pyroltrilinos.libs/libstdc++-5d72f927.so.6.0.33
pyroltrilinos-0.5.6.dist-info/LICENSE.txt
pyroltrilinos-0.5.6.dist-info/METADATA
pyroltrilinos-0.5.6.dist-info/WHEEL
pyroltrilinos-0.5.6.dist-info/top_level.txt
pyroltrilinos-0.5.6.dist-info/RECORD
