Metadata-Version: 2.4
Name: pyroltrilinos
Version: 0.5.6
Summary: A Python wrapper for the ROL package
Author: Chris Richardson, Greg von Winckel, Florian Wechsung, Angus Gibson
Maintainer: Angus Gibson
Project-URL: homepage, https://github.com/angus-g/pyrol
Classifier: License :: OSI Approved :: GNU Lesser General Public License v3 (LGPLv3)
Classifier: Programming Language :: Python :: 3
License-File: LICENSE.txt
Dynamic: license-file
